LICENSE.txt
README.md
setup.cfg
setup.py
FastInput/__init__.py
FastInput/fast_input.py
FastInput.egg-info/PKG-INFO
FastInput.egg-info/SOURCES.txt
FastInput.egg-info/dependency_links.txt
FastInput.egg-info/top_level.txt