Metadata-Version: 2.1
Name: FastInput
Version: 0.3
Summary: A package that wrap the input function with validation
Home-page: https://github.com/alexwtz/fastInput
Download-URL: https://github.com/alexwtz/FastInput/archive/refs/tags/0.3.tar.gz
Author: Alexandre Wetzel
Author-email: alexwtz@gmail.com
License: MIT
Keywords: input,validation,prompt
Classifier: Development Status :: 3 - Alpha
Classifier: Intended Audience :: Developers
Classifier: Topic :: Software Development :: Build Tools
Classifier: License :: OSI Approved :: MIT License
Classifier: Programming Language :: Python :: 3
Classifier: Programming Language :: Python :: 3.4
Classifier: Programming Language :: Python :: 3.5
Classifier: Programming Language :: Python :: 3.6
License-File: LICENSE.txt
